mqtt2measurinator/__init__.py
mqtt2measurinator/cli.py
mqtt2measurinator-0.1.4.dist-info/METADATA
mqtt2measurinator-0.1.4.dist-info/WHEEL
mqtt2measurinator-0.1.4.dist-info/entry_points.txt
mqtt2measurinator-0.1.4.dist-info/top_level.txt
mqtt2measurinator-0.1.4.dist-info/RECORD
